[
  {
    "user": "taynara",
    "senha": "teste123"
  },
  {
    "user": "taynara",
    "senha": "teste123"
  },
  {
    "user": "21",
    "senha": "1"
  },
  {
    "user": "21",
    "senha": "1"
  },
  {
    "user": "gfh",
    "senha": "oi"
  },
  {
    "user": "gfh",
    "senha": "oi"
  },
  {
    "user": "davi",
    "senha": "certo"
  },
  {
    "user": "davi",
    "senha": "certo"
  },
  {
    "user": "davi certo",
    "senha": "aa"
  },
  {
    "user": "adas",
    "senha": "senha certa"
  }
]